btsniff/__init__.py
btsniff/app.py
btsniff/core/__init__.py
btsniff/core/_chrome.py
btsniff/core/_parser.py
btsniff/data/bbt.yaml
btsniff/data/btdx8.yaml
btsniff/data/dygod.yaml
btsniff/sites/__init__.py
btsniff/sites/bbt.py
btsniff/sites/btdx8.py
btsniff/sites/dygod.py
btsniff-0.0.2.dist-info/LICENSE
btsniff-0.0.2.dist-info/METADATA
btsniff-0.0.2.dist-info/WHEEL
btsniff-0.0.2.dist-info/entry_points.txt
btsniff-0.0.2.dist-info/top_level.txt
btsniff-0.0.2.dist-info/RECORD
